Synthesis/exec/sampleandhold.v
module sampleandhold(
	output cmp,
	input [63:0] analog_in,
	input sample,
	input [7:0] value
	);

	//Sample and hold
	real hold;
	always@(posedge sample) 
		hold = $bitstoreal(analog_in);
	
	// compare the generated signal with the input
	assign cmp = (hold >= value);	


endmodule

Synthesis/exec/SAR_RTL.v
module ADC_SAR1(
	output reg [7:0] digital_out,	//8 bit digital output
	output out_flag,			 	//will be 1 when conversion is completed				
	output sample,
	output [7:0] value,
	input checker,
	input cmp,
	input clk,						//clock input
	input enable					//enable signal which drives the module
	);
	
	//State assignment for all combinations
	parameter STATE_WAIT = 0;
	parameter STATE_SAMPLE = 1;
	parameter STATE_CONVERT = 2;
	parameter STATE_DONE = 3;
	
	//connection assignment
	
	reg [1:0] state;
	reg [7:0] temp;
	reg [7:0] result;
	
	
	//* SAR code generation
	//* Comparision of input signal
	//* updating the result and digital_out
	always@(posedge clk) begin
		if(!enable) 
			state <= STATE_WAIT;
		else begin
			case(state)
				STATE_WAIT:								//wait until enable is 1 and sample of input is aquired	
					state <= STATE_SAMPLE;
				STATE_SAMPLE:begin						//capture sampl and initialize SAR registers
					state <= STATE_CONVERT;
					temp <= 8'b10000000;
					result <= 8'b0;
				end
				STATE_CONVERT:begin						
				//compare the signal with SAR generated signal and update with respect to temp value
					if(cmp) 
						result <= result | temp;
					temp <= temp >> 1;
					if(temp[0]) 
						state <= STATE_DONE;
					end
				STATE_DONE:begin						//Tap the result ot output
					digital_out <= result;
					if(enable)
						state <= STATE_WAIT;
					end
			endcase
		end		
	end
	//update the status of flags
	assign sample = (state == STATE_SAMPLE);
	assign value = result | temp;
	assign out_flag = (state == STATE_DONE);
	
endmodule

Synthesis/exec/SAR_TB.v

module testbench;

	reg clk;
	reg	enable;
	wire out_flag;
	wire [7:0] digital_out;
	
	localparam clk_pd = 80; 			//*	(clock period * clock cycles) i.e:(10*8) for this code 
	localparam real step   = 1;			// stepsize
	localparam real nsteps = 100;		// Number of samples
	localparam real maxval = 11.0;		// largest input 
	localparam real minval = 0.0;		// Minimum input
	real analogsig;
	reg [63:0] analog_disc;
	
	initial begin
    	$dumpfile("traces");
    	$dumpvars;
    end
    
	//initialize the test bench stimulus
	initial begin : stimulus 
    integer i;
    real sign;
    sign = 1.0;

	//function to generate real valued signal varing from 0 -> 11
    for (i = 0; i < nsteps ; i = i + 1)
		begin
			#clk_pd;
		   analogsig = analogsig + (sign * step);
		   if (analogsig >= maxval)
			  sign = -1.0;
		   if (analogsig <= minval)
			  sign = +1.0;      
		   analog_disc = $realtobits(analogsig);
		end
	 $stop;
	end  
	
	wire cmp;
	wire [7:0] value;
	wire sample;


	// instantiate the Design module
	ADC_SAR1 uut(
				.out_flag(out_flag),
				.digital_out(digital_out),
				.clk(clk),
				.enable(enable),
				.cmp(cmp),
				.sample(sample),
				.value(value)
				);
	
	//connect sample and hold network to the design module
	sampleandhold uut1(
				.cmp(cmp),
				.analog_in(analog_disc),
				.sample(sample),
				.value(value)
				);

	//Generate clock signal
	always begin
		clk = ~clk; #5;
	end
	initial clk = 1'b0;
	
	//display required values to the output console
	initial begin 
		$monitor($time, "enable=%b out_flag=%b result=%b sample=%b uut.value=%b cmp=%b uut.state=%b mask=%b",enable,out_flag,digital_out,uut.sample,uut.value,uut.cmp,uut.state,uut.temp);

	#100; enable = 0;
	#100; enable = 1;
//	#2000;
//	$stop;
	end
endmodule

Synthesis/tb/traces.vcd
$date
    Mar  2, 2021  13:45:38
$end
$version
    TOOL:	ncsim(64)	15.20-s069
$end
$timescale
    1 ns
$end

$scope module testbench $end
$var reg       1 !    clk  $end
$var reg       1 "    enable  $end
$var wire      1 #    out_flag  $end
$var wire      8 $    digital_out [7:0] $end
$var parameter 32 %    clk_pd  $end
$var real     64 &    step  $end
$var real     64 '    nsteps  $end
$var real     64 (    maxval  $end
$var real     64 )    minval  $end
$var real     64 *    analogsig  $end
$var reg      64 +    analog_disc [63:0] $end
$var wire      1 ,    cmp  $end
$var wire      8 -    value [7:0] $end
$var wire      1 .    sample  $end

$scope begin stimulus $end
$var integer  32 /    i  $end
$var real     64 0    sign  $end
$upscope $end


$scope module uut $end
$var reg       8 1    digital_out [7:0] $end
$var wire      1 #    out_flag  $end
$var wire      1 .    sample  $end
$var wire      8 -    value [7:0] $end
$var wire      1 2    checker  $end
$var wire      1 ,    cmp  $end
$var wire      1 3    clk  $end
$var wire      1 4    enable  $end
$var parameter 32 5    STATE_WAIT  $end
$var parameter 32 6    STATE_SAMPLE  $end
$var parameter 32 7    STATE_CONVERT  $end
$var parameter 32 8    STATE_DONE  $end
$var reg       2 9    state [1:0] $end
$var reg       8 :    temp [7:0] $end
$var reg       8 ;    result [7:0] $end
$upscope $end


$scope module uut1 $end
$var wire      1 ,    cmp  $end
$var wire     64 <    analog_in [63:0] $end
$var wire      1 .    sample  $end
$var wire      8 -    value [7:0] $end
$var real     64 =    hold  $end
$upscope $end

$upscope $end

$enddefinitions $end
$dumpvars
b11 8
b10 7
b1 6
b0 5
r0 )
r11 (
r100 '
r1 &
b1010000 %
0!
x"
x#
bx $
r0 *
bx +
1,
bx -
x.
b0 /
r1 0
bx 1
z2
03
x4
bx 9
bx :
bx ;
bx <
r0 =
$end
#5
1!
13
#10
0!
03
#15
1!
13
#20
0!
03
#25
1!
13
#30
0!
03
#35
1!
13
#40
0!
03
#45
1!
13
#50
0!
03
#55
1!
13
#60
0!
03
#65
1!
13
#70
0!
03
#75
1!
13
#80
r1 *
b11111111110000000000000000000000000000000000000000000000000000 +
b1 /
0!
03
b11111111110000000000000000000000000000000000000000000000000000 <
#85
1!
13
#90
0!
03
#95
1!
13
#100
0"
0!
03
04
#105
1!
13
b0 9
0#
0.
#110
0!
03
#115
1!
13
#120
0!
03
#125
1!
13
#130
0!
03
#135
1!
13
#140
0!
03
#145
1!
13
#150
0!
03
#155
1!
13
#160
r2 *
b100000000000000000000000000000000000000000000000000000000000000 +
b10 /
0!
03
b100000000000000000000000000000000000000000000000000000000000000 <
#165
1!
13
#170
0!
03
#175
1!
13
#180
0!
03
#185
1!
13
#190
0!
03
#195
1!
13
#200
1"
0!
03
14
#205
1!
13
b1 9
1.
r2 =
#210
0!
03
#215
1!
13
b10 9
b10000000 :
b0 ;
b10000000 -
0.
0,
#220
0!
03
#225
1!
13
b1000000 :
b1000000 -
#230
0!
03
#235
1!
13
b100000 :
b100000 -
#240
r3 *
b100000000001000000000000000000000000000000000000000000000000000 +
b11 /
0!
03
b100000000001000000000000000000000000000000000000000000000000000 <
#245
1!
13
b10000 :
b10000 -
#250
0!
03
#255
1!
13
b1000 :
b1000 -
#260
0!
03
#265
1!
13
b100 :
b100 -
#270
0!
03
#275
1!
13
b10 :
b10 -
1,
#280
0!
03
#285
1!
13
b10 ;
b1 :
b11 -
0,
#290
0!
03
#295
1!
13
b0 :
b11 9
1#
b10 -
1,
#300
0!
03
#305
1!
13
b10 1
b0 9
0#
b10 $
#310
0!
03
#315
1!
13
b1 9
1.
r3 =
#320
r4 *
b100000000010000000000000000000000000000000000000000000000000000 +
b100 /
0!
03
b100000000010000000000000000000000000000000000000000000000000000 <
#325
1!
13
b10 9
b10000000 :
b0 ;
b10000000 -
0.
0,
#330
0!
03
#335
1!
13
b1000000 :
b1000000 -
#340
0!
03
#345
1!
13
b100000 :
b100000 -
#350
0!
03
#355
1!
13
b10000 :
b10000 -
#360
0!
03
#365
1!
13
b1000 :
b1000 -
#370
0!
03
#375
1!
13
b100 :
b100 -
#380
0!
03
#385
1!
13
b10 :
b10 -
1,
#390
0!
03
#395
1!
13
b10 ;
b1 :
b11 -
#400
r5 *
b100000000010100000000000000000000000000000000000000000000000000 +
b101 /
0!
03
b100000000010100000000000000000000000000000000000000000000000000 <
#405
1!
13
b11 ;
b0 :
b11 9
1#
#410
0!
03
#415
1!
13
b11 1
b0 9
0#
b11 $
#420
0!
03
#425
1!
13
b1 9
1.
r5 =
#430
0!
03
#435
1!
13
b10 9
b10000000 :
b0 ;
b10000000 -
0.
0,
#440
0!
03
#445
1!
13
b1000000 :
b1000000 -
#450
0!
03
#455
1!
13
b100000 :
b100000 -
#460
0!
03
#465
1!
13
b10000 :
b10000 -
#470
0!
03
#475
1!
13
b1000 :
b1000 -
#480
r6 *
b100000000011000000000000000000000000000000000000000000000000000 +
b110 /
0!
03
b100000000011000000000000000000000000000000000000000000000000000 <
#485
1!
13
b100 :
b100 -
1,
#490
0!
03
#495
1!
13
b100 ;
b10 :
b110 -
0,
#500
0!
03
#505
1!
13
b1 :
b101 -
1,
#510
0!
03
#515
1!
13
b101 ;
b0 :
b11 9
1#
#520
0!
03
#525
1!
13
b101 1
b0 9
0#
b101 $
#530
0!
03
#535
1!
13
b1 9
1.
r6 =
#540
0!
03
#545
1!
13
b10 9
b10000000 :
b0 ;
b10000000 -
0.
0,
#550
0!
03
#555
1!
13
b1000000 :
b1000000 -
#560
r7 *
b100000000011100000000000000000000000000000000000000000000000000 +
b111 /
0!
03
b100000000011100000000000000000000000000000000000000000000000000 <
#565
1!
13
b100000 :
b100000 -
#570
0!
03
#575
1!
13
b10000 :
b10000 -
#580
0!
03
#585
1!
13
b1000 :
b1000 -
#590
0!
03
#595
1!
13
b100 :
b100 -
1,
#600
0!
03
#605
1!
13
b100 ;
b10 :
b110 -
#610
0!
03
#615
1!
13
b110 ;
b1 :
b111 -
0,
#620
0!
03
#625
1!
13
b0 :
b11 9
1#
b110 -
1,
#630
0!
03
#635
1!
13
b110 1
b0 9
0#
b110 $
#640
r8 *
b100000000100000000000000000000000000000000000000000000000000000 +
b1000 /
0!
03
b100000000100000000000000000000000000000000000000000000000000000 <
#645
1!
13
b1 9
1.
r8 =
#650
0!
03
#655
1!
13
b10 9
b10000000 :
b0 ;
b10000000 -
0.
0,
#660
0!
03
#665
1!
13
b1000000 :
b1000000 -
#670
0!
03
#675
1!
13
b100000 :
b100000 -
#680
0!
03
#685
1!
13
b10000 :
b10000 -
#690
0!
03
#695
1!
13
b1000 :
b1000 -
1,
#700
0!
03
#705
1!
13
b1000 ;
b100 :
b1100 -
0,
#710
0!
03
#715
1!
13
b10 :
b1010 -
#720
r9 *
b100000000100010000000000000000000000000000000000000000000000000 +
b1001 /
0!
03
b100000000100010000000000000000000000000000000000000000000000000 <
#725
1!
13
b1 :
b1001 -
#730
0!
03
#735
1!
13
b0 :
b11 9
1#
b1000 -
1,
#740
0!
03
#745
1!
13
b1000 1
b0 9
0#
b1000 $
#750
0!
03
#755
1!
13
b1 9
1.
r9 =
#760
0!
03
#765
1!
13
b10 9
b10000000 :
b0 ;
b10000000 -
0.
0,
#770
0!
03
#775
1!
13
b1000000 :
b1000000 -
#780
0!
03
#785
1!
13
b100000 :
b100000 -
#790
0!
03
#795
1!
13
b10000 :
b10000 -
#800
r10 *
b100000000100100000000000000000000000000000000000000000000000000 +
b1010 /
0!
03
b100000000100100000000000000000000000000000000000000000000000000 <
#805
1!
13
b1000 :
b1000 -
1,
#810
0!
03
#815
1!
13
b1000 ;
b100 :
b1100 -
0,
#820
0!
03
#825
1!
13
b10 :
b1010 -
#830
0!
03
#835
1!
13
b1 :
b1001 -
1,
#840
0!
03
#845
1!
13
b1001 ;
b0 :
b11 9
1#
#850
0!
03
#855
1!
13
b1001 1
b0 9
0#
b1001 $
#860
0!
03
#865
1!
13
b1 9
1.
r10 =
#870
0!
03
#875
1!
13
b10 9
b10000000 :
b0 ;
b10000000 -
0.
0,
#880
r11 *
r-1 0
b100000000100110000000000000000000000000000000000000000000000000 +
b1011 /
0!
03
b100000000100110000000000000000000000000000000000000000000000000 <
#885
1!
13
b1000000 :
b1000000 -
#890
0!
03
#895
1!
13
b100000 :
b100000 -
#900
0!
03
#905
1!
13
b10000 :
b10000 -
#910
0!
03
#915
1!
13
b1000 :
b1000 -
1,
#920
0!
03
#925
1!
13
b1000 ;
b100 :
b1100 -
0,
#930
0!
03
#935
1!
13
b10 :
b1010 -
1,
#940
0!
03
#945
1!
13
b1010 ;
b1 :
b1011 -
0,
#950
0!
03
#955
1!
13
b0 :
b11 9
1#
b1010 -
1,
#960
r10 *
b100000000100100000000000000000000000000000000000000000000000000 +
b1100 /
0!
03
b100000000100100000000000000000000000000000000000000000000000000 <
#965
1!
13
b1010 1
b0 9
0#
b1010 $
#970
0!
03
#975
1!
13
b1 9
1.
#980
0!
03
#985
1!
13
b10 9
b10000000 :
b0 ;
b10000000 -
0.
0,
#990
0!
03
#995
1!
13
b1000000 :
b1000000 -
#1000
0!
03
#1005
1!
13
b100000 :
b100000 -
#1010
0!
03
#1015
1!
13
b10000 :
b10000 -
#1020
0!
03
#1025
1!
13
b1000 :
b1000 -
1,
#1030
0!
03
#1035
1!
13
b1000 ;
b100 :
b1100 -
0,
#1040
r9 *
b100000000100010000000000000000000000000000000000000000000000000 +
b1101 /
0!
03
b100000000100010000000000000000000000000000000000000000000000000 <
#1045
1!
13
b10 :
b1010 -
1,
#1050
0!
03
#1055
1!
13
b1010 ;
b1 :
b1011 -
0,
#1060
0!
03
#1065
1!
13
b0 :
b11 9
1#
b1010 -
1,
#1070
0!
03
#1075
1!
13
b0 9
0#
#1080
0!
03
#1085
1!
13
b1 9
1.
r9 =
0,
#1090
0!
03
#1095
1!
13
b10 9
b10000000 :
b0 ;
b10000000 -
0.
#1100
0!
03
#1105
1!
13
b1000000 :
b1000000 -
#1110
0!
03
#1115
1!
13
b100000 :
b100000 -
#1120
r8 *
b100000000100000000000000000000000000000000000000000000000000000 +
b1110 /
0!
03
b100000000100000000000000000000000000000000000000000000000000000 <
#1125
1!
13
b10000 :
b10000 -
#1130
0!
03
#1135
1!
13
b1000 :
b1000 -
1,
#1140
0!
03
#1145
1!
13
b1000 ;
b100 :
b1100 -
0,
#1150
0!
03
#1155
1!
13
b10 :
b1010 -
#1160
0!
03
#1165
1!
13
b1 :
b1001 -
1,
#1170
0!
03
#1175
1!
13
b1001 ;
b0 :
b11 9
1#
#1180
0!
03
#1185
1!
13
b1001 1
b0 9
0#
b1001 $
#1190
0!
03
#1195
1!
13
b1 9
1.
r8 =
0,
#1200
r7 *
b100000000011100000000000000000000000000000000000000000000000000 +
b1111 /
0!
03
b100000000011100000000000000000000000000000000000000000000000000 <
#1205
1!
13
b10 9
b10000000 :
b0 ;
b10000000 -
0.
#1210
0!
03
#1215
1!
13
b1000000 :
b1000000 -
#1220
0!
03
#1225
1!
13
b100000 :
b100000 -
#1230
0!
03
#1235
1!
13
b10000 :
b10000 -
#1240
0!
03
#1245
1!
13
b1000 :
b1000 -
1,
#1250
0!
03
#1255
1!
13
b1000 ;
b100 :
b1100 -
0,
#1260
0!
03
#1265
1!
13
b10 :
b1010 -
#1270
0!
03
#1275
1!
13
b1 :
b1001 -
#1280
r6 *
b100000000011000000000000000000000000000000000000000000000000000 +
b10000 /
0!
03
b100000000011000000000000000000000000000000000000000000000000000 <
#1285
1!
13
b0 :
b11 9
1#
b1000 -
1,
#1290
0!
03
#1295
1!
13
b1000 1
b0 9
0#
b1000 $
#1300
0!
03
#1305
1!
13
b1 9
1.
r6 =
0,
#1310
0!
03
#1315
1!
13
b10 9
b10000000 :
b0 ;
b10000000 -
0.
#1320
0!
03
#1325
1!
13
b1000000 :
b1000000 -
#1330
0!
03
#1335
1!
13
b100000 :
b100000 -
#1340
0!
03
#1345
1!
13
b10000 :
b10000 -
#1350
0!
03
#1355
1!
13
b1000 :
b1000 -
#1360
r5 *
b100000000010100000000000000000000000000000000000000000000000000 +
b10001 /
0!
03
b100000000010100000000000000000000000000000000000000000000000000 <
#1365
1!
13
b100 :
b100 -
1,
#1370
0!
03
#1375
1!
13
b100 ;
b10 :
b110 -
#1380
0!
03
#1385
1!
13
b110 ;
b1 :
b111 -
0,
#1390
0!
03
#1395
1!
13
b0 :
b11 9
1#
b110 -
1,
#1400
0!
03
#1405
1!
13
b110 1
b0 9
0#
b110 $
#1410
0!
03
#1415
1!
13
b1 9
1.
r5 =
0,
#1420
0!
03
#1425
1!
13
b10 9
b10000000 :
b0 ;
b10000000 -
0.
#1430
0!
03
#1435
1!
13
b1000000 :
b1000000 -
#1440
r4 *
b100000000010000000000000000000000000000000000000000000000000000 +
b10010 /
0!
03
b100000000010000000000000000000000000000000000000000000000000000 <
#1445
1!
13
b100000 :
b100000 -
#1450
0!
03
#1455
1!
13
b10000 :
b10000 -
#1460
0!
03
#1465
1!
13
b1000 :
b1000 -
#1470
0!
03
#1475
1!
13
b100 :
b100 -
1,
#1480
0!
03
#1485
1!
13
b100 ;
b10 :
b110 -
0,
#1490
0!
03
#1495
1!
13
b1 :
b101 -
1,
#1500
0!
03
#1505
1!
13
b101 ;
b0 :
b11 9
1#
#1510
0!
03
#1515
1!
13
b101 1
b0 9
0#
b101 $
#1520
r3 *
b100000000001000000000000000000000000000000000000000000000000000 +
b10011 /
0!
03
b100000000001000000000000000000000000000000000000000000000000000 <
#1525
1!
13
b1 9
1.
r3 =
0,
#1530
0!
03
#1535
1!
13
b10 9
b10000000 :
b0 ;
b10000000 -
0.
#1540
0!
03
#1545
1!
13
b1000000 :
b1000000 -
#1550
0!
03
#1555
1!
13
b100000 :
b100000 -
#1560
0!
03
#1565
1!
13
b10000 :
b10000 -
#1570
0!
03
#1575
1!
13
b1000 :
b1000 -
#1580
0!
03
#1585
1!
13
b100 :
b100 -
#1590
0!
03
#1595
1!
13
b10 :
b10 -
1,
#1600
r2 *
b100000000000000000000000000000000000000000000000000000000000000 +
b10100 /
0!
03
b100000000000000000000000000000000000000000000000000000000000000 <
#1605
1!
13
b10 ;
b1 :
b11 -
#1610
0!
03
#1615
1!
13
b11 ;
b0 :
b11 9
1#
#1620
0!
03
#1625
1!
13
b11 1
b0 9
0#
b11 $
#1630
0!
03
#1635
1!
13
b1 9
1.
r2 =
0,
#1640
0!
03
#1645
1!
13
b10 9
b10000000 :
b0 ;
b10000000 -
0.
#1650
0!
03
#1655
1!
13
b1000000 :
b1000000 -
#1660
0!
03
#1665
1!
13
b100000 :
b100000 -
#1670
0!
03
#1675
1!
13
b10000 :
b10000 -
#1680
r1 *
b11111111110000000000000000000000000000000000000000000000000000 +
b10101 /
0!
03
b11111111110000000000000000000000000000000000000000000000000000 <
#1685
1!
13
b1000 :
b1000 -
#1690
0!
03
#1695
1!
13
b100 :
b100 -
#1700
0!
03
#1705
1!
13
b10 :
b10 -
1,
#1710
0!
03
#1715
1!
13
b10 ;
b1 :
b11 -
0,
#1720
0!
03
#1725
1!
13
b0 :
b11 9
1#
b10 -
1,
#1730
0!
03
#1735
1!
13
b10 1
b0 9
0#
b10 $
#1740
0!
03
#1745
1!
13
b1 9
1.
r1 =
0,
#1750
0!
03
#1755
1!
13
b10 9
b10000000 :
b0 ;
b10000000 -
0.
#1760
r0 *
r1 0
b0 +
b10110 /
0!
03
b0 <
#1765
1!
13
b1000000 :
b1000000 -
#1770
0!
03
#1775
1!
13
b100000 :
b100000 -
#1780
0!
03
#1785
1!
13
b10000 :
b10000 -
#1790
0!
03
#1795
1!
13
b1000 :
b1000 -
#1800
0!
03
#1805
1!
13
b100 :
b100 -
#1810
0!
03
#1815
1!
13
b10 :
b10 -
#1820
0!
03
#1825
1!
13
b1 :
b1 -
1,
#1830
0!
03
#1835
1!
13
b1 ;
b0 :
b11 9
1#
#1840
r1 *
b11111111110000000000000000000000000000000000000000000000000000 +
b10111 /
0!
03
b11111111110000000000000000000000000000000000000000000000000000 <
#1845
1!
13
b1 1
b0 9
0#
b1 $
#1850
0!
03
#1855
1!
13
b1 9
1.
#1860
0!
03
#1865
1!
13
b10 9
b10000000 :
b0 ;
b10000000 -
0.
0,
#1870
0!
03
#1875
1!
13
b1000000 :
b1000000 -
#1880
0!
03
#1885
1!
13
b100000 :
b100000 -
#1890
0!
03
#1895
1!
13
b10000 :
b10000 -
#1900
0!
03
#1905
1!
13
b1000 :
b1000 -
#1910
0!
03
#1915
1!
13
b100 :
b100 -
#1920
r2 *
b100000000000000000000000000000000000000000000000000000000000000 +
b11000 /
0!
03
b100000000000000000000000000000000000000000000000000000000000000 <
#1925
1!
13
b10 :
b10 -
#1930
0!
03
#1935
1!
13
b1 :
b1 -
1,
#1940
0!
03
#1945
1!
13
b1 ;
b0 :
b11 9
1#
#1950
0!
03
#1955
1!
13
b0 9
0#
#1960
0!
03
#1965
1!
13
b1 9
1.
r2 =
#1970
0!
03
#1975
1!
13
b10 9
b10000000 :
b0 ;
b10000000 -
0.
0,
#1980
0!
03
#1985
1!
13
b1000000 :
b1000000 -
#1990
0!
03
#1995
1!
13
b100000 :
b100000 -
#2000
r3 *
b100000000001000000000000000000000000000000000000000000000000000 +
b11001 /
0!
03
b100000000001000000000000000000000000000000000000000000000000000 <
#2005
1!
13
b10000 :
b10000 -
#2010
0!
03
#2015
1!
13
b1000 :
b1000 -
#2020
0!
03
#2025
1!
13
b100 :
b100 -
#2030
0!
03
#2035
1!
13
b10 :
b10 -
1,
#2040
0!
03
#2045
1!
13
b10 ;
b1 :
b11 -
0,
#2050
0!
03
#2055
1!
13
b0 :
b11 9
1#
b10 -
1,
#2060
0!
03
#2065
1!
13
b10 1
b0 9
0#
b10 $
#2070
0!
03
#2075
1!
13
b1 9
1.
r3 =
#2080
r4 *
b100000000010000000000000000000000000000000000000000000000000000 +
b11010 /
0!
03
b100000000010000000000000000000000000000000000000000000000000000 <
#2085
1!
13
b10 9
b10000000 :
b0 ;
b10000000 -
0.
0,
#2090
0!
03
#2095
1!
13
b1000000 :
b1000000 -
#2100
0!
03
#2105
1!
13
b100000 :
b100000 -
#2110
0!
03
#2115
1!
13
b10000 :
b10000 -
#2120
0!
03
#2125
1!
13
b1000 :
b1000 -
#2130
0!
03
#2135
1!
13
b100 :
b100 -
#2140
0!
03
#2145
1!
13
b10 :
b10 -
1,
#2150
0!
03
#2155
1!
13
b10 ;
b1 :
b11 -
#2160
r5 *
b100000000010100000000000000000000000000000000000000000000000000 +
b11011 /
0!
03
b100000000010100000000000000000000000000000000000000000000000000 <
#2165
1!
13
b11 ;
b0 :
b11 9
1#
#2170
0!
03
#2175
1!
13
b11 1
b0 9
0#
b11 $
#2180
0!
03
#2185
1!
13
b1 9
1.
r5 =
#2190
0!
03
#2195
1!
13
b10 9
b10000000 :
b0 ;
b10000000 -
0.
0,
#2200
0!
03
#2205
1!
13
b1000000 :
b1000000 -
#2210
0!
03
#2215
1!
13
b100000 :
b100000 -
#2220
0!
03
#2225
1!
13
b10000 :
b10000 -
#2230
0!
03
#2235
1!
13
b1000 :
b1000 -
#2240
r6 *
b100000000011000000000000000000000000000000000000000000000000000 +
b11100 /
0!
03
b100000000011000000000000000000000000000000000000000000000000000 <
#2245
1!
13
b100 :
b100 -
1,
#2250
0!
03
#2255
1!
13
b100 ;
b10 :
b110 -
0,
#2260
0!
03
#2265
1!
13
b1 :
b101 -
1,
#2270
0!
03
#2275
1!
13
b101 ;
b0 :
b11 9
1#
#2280
0!
03
#2285
1!
13
b101 1
b0 9
0#
b101 $
#2290
0!
03
#2295
1!
13
b1 9
1.
r6 =
#2300
0!
03
#2305
1!
13
b10 9
b10000000 :
b0 ;
b10000000 -
0.
0,
#2310
0!
03
#2315
1!
13
b1000000 :
b1000000 -
#2320
r7 *
b100000000011100000000000000000000000000000000000000000000000000 +
b11101 /
0!
03
b100000000011100000000000000000000000000000000000000000000000000 <
#2325
1!
13
b100000 :
b100000 -
#2330
0!
03
#2335
1!
13
b10000 :
b10000 -
#2340
0!
03
#2345
1!
13
b1000 :
b1000 -
#2350
0!
03
#2355
1!
13
b100 :
b100 -
1,
#2360
0!
03
#2365
1!
13
b100 ;
b10 :
b110 -
#2370
0!
03
#2375
1!
13
b110 ;
b1 :
b111 -
0,
#2380
0!
03
#2385
1!
13
b0 :
b11 9
1#
b110 -
1,
#2390
0!
03
#2395
1!
13
b110 1
b0 9
0#
b110 $
#2400
r8 *
b100000000100000000000000000000000000000000000000000000000000000 +
b11110 /
0!
03
b100000000100000000000000000000000000000000000000000000000000000 <
#2405
1!
13
b1 9
1.
r8 =
#2410
0!
03
#2415
1!
13
b10 9
b10000000 :
b0 ;
b10000000 -
0.
0,
#2420
0!
03
#2425
1!
13
b1000000 :
b1000000 -
#2430
0!
03
#2435
1!
13
b100000 :
b100000 -
#2440
0!
03
#2445
1!
13
b10000 :
b10000 -
#2450
0!
03
#2455
1!
13
b1000 :
b1000 -
1,
#2460
0!
03
#2465
1!
13
b1000 ;
b100 :
b1100 -
0,
#2470
0!
03
#2475
1!
13
b10 :
b1010 -
#2480
r9 *
b100000000100010000000000000000000000000000000000000000000000000 +
b11111 /
0!
03
b100000000100010000000000000000000000000000000000000000000000000 <
#2485
1!
13
b1 :
b1001 -
#2490
0!
03
#2495
1!
13
b0 :
b11 9
1#
b1000 -
1,
#2500
0!
03
#2505
1!
13
b1000 1
b0 9
0#
b1000 $
#2510
0!
03
#2515
1!
13
b1 9
1.
r9 =
#2520
0!
03
#2525
1!
13
b10 9
b10000000 :
b0 ;
b10000000 -
0.
0,
#2530
0!
03
#2535
1!
13
b1000000 :
b1000000 -
#2540
0!
03
#2545
1!
13
b100000 :
b100000 -
#2550
0!
03
#2555
1!
13
b10000 :
b10000 -
#2560
r10 *
b100000000100100000000000000000000000000000000000000000000000000 +
b100000 /
0!
03
b100000000100100000000000000000000000000000000000000000000000000 <
#2565
1!
13
b1000 :
b1000 -
1,
#2570
0!
03
#2575
1!
13
b1000 ;
b100 :
b1100 -
0,
#2580
0!
03
#2585
1!
13
b10 :
b1010 -
#2590
0!
03
#2595
1!
13
b1 :
b1001 -
1,
#2600
0!
03
#2605
1!
13
b1001 ;
b0 :
b11 9
1#
#2610
0!
03
#2615
1!
13
b1001 1
b0 9
0#
b1001 $
#2620
0!
03
#2625
1!
13
b1 9
1.
r10 =
#2630
0!
03
#2635
1!
13
b10 9
b10000000 :
b0 ;
b10000000 -
0.
0,
#2640
r11 *
r-1 0
b100000000100110000000000000000000000000000000000000000000000000 +
b100001 /
0!
03
b100000000100110000000000000000000000000000000000000000000000000 <
#2645
1!
13
b1000000 :
b1000000 -
#2650
0!
03
#2655
1!
13
b100000 :
b100000 -
#2660
0!
03
#2665
1!
13
b10000 :
b10000 -
#2670
0!
03
#2675
1!
13
b1000 :
b1000 -
1,
#2680
0!
03
#2685
1!
13
b1000 ;
b100 :
b1100 -
0,
#2690
0!
03
#2695
1!
13
b10 :
b1010 -
1,
#2700
0!
03
#2705
1!
13
b1010 ;
b1 :
b1011 -
0,
#2710
0!
03
#2715
1!
13
b0 :
b11 9
1#
b1010 -
1,
#2720
r10 *
b100000000100100000000000000000000000000000000000000000000000000 +
b100010 /
0!
03
b100000000100100000000000000000000000000000000000000000000000000 <
#2725
1!
13
b1010 1
b0 9
0#
b1010 $
#2730
0!
03
#2735
1!
13
b1 9
1.
#2740
0!
03
#2745
1!
13
b10 9
b10000000 :
b0 ;
b10000000 -
0.
0,
#2750
0!
03
#2755
1!
13
b1000000 :
b1000000 -
#2760
0!
03
#2765
1!
13
b100000 :
b100000 -
#2770
0!
03
#2775
1!
13
b10000 :
b10000 -
#2780
0!
03
#2785
1!
13
b1000 :
b1000 -
1,
#2790
0!
03
#2795
1!
13
b1000 ;
b100 :
b1100 -
0,
#2800
r9 *
b100000000100010000000000000000000000000000000000000000000000000 +
b100011 /
0!
03
b100000000100010000000000000000000000000000000000000000000000000 <
#2805
1!
13
b10 :
b1010 -
1,
#2810
0!
03
#2815
1!
13
b1010 ;
b1 :
b1011 -
0,
#2820
0!
03
#2825
1!
13
b0 :
b11 9
1#
b1010 -
1,
#2830
0!
03
#2835
1!
13
b0 9
0#
#2840
0!
03
#2845
1!
13
b1 9
1.
r9 =
0,
#2850
0!
03
#2855
1!
13
b10 9
b10000000 :
b0 ;
b10000000 -
0.
#2860
0!
03
#2865
1!
13
b1000000 :
b1000000 -
#2870
0!
03
#2875
1!
13
b100000 :
b100000 -
#2880
r8 *
b100000000100000000000000000000000000000000000000000000000000000 +
b100100 /
0!
03
b100000000100000000000000000000000000000000000000000000000000000 <
#2885
1!
13
b10000 :
b10000 -
#2890
0!
03
#2895
1!
13
b1000 :
b1000 -
1,
#2900
0!
03
#2905
1!
13
b1000 ;
b100 :
b1100 -
0,
#2910
0!
03
#2915
1!
13
b10 :
b1010 -
#2920
0!
03
#2925
1!
13
b1 :
b1001 -
1,
#2930
0!
03
#2935
1!
13
b1001 ;
b0 :
b11 9
1#
#2940
0!
03
#2945
1!
13
b1001 1
b0 9
0#
b1001 $
#2950
0!
03
#2955
1!
13
b1 9
1.
r8 =
0,
#2960
r7 *
b100000000011100000000000000000000000000000000000000000000000000 +
b100101 /
0!
03
b100000000011100000000000000000000000000000000000000000000000000 <
#2965
1!
13
b10 9
b10000000 :
b0 ;
b10000000 -
0.
#2970
0!
03
#2975
1!
13
b1000000 :
b1000000 -
#2980
0!
03
#2985
1!
13
b100000 :
b100000 -
#2990
0!
03
#2995
1!
13
b10000 :
b10000 -
#3000
0!
03
#3005
1!
13
b1000 :
b1000 -
1,
#3010
0!
03
#3015
1!
13
b1000 ;
b100 :
b1100 -
0,
#3020
0!
03
#3025
1!
13
b10 :
b1010 -
#3030
0!
03
#3035
1!
13
b1 :
b1001 -
#3040
r6 *
b100000000011000000000000000000000000000000000000000000000000000 +
b100110 /
0!
03
b100000000011000000000000000000000000000000000000000000000000000 <
#3045
1!
13
b0 :
b11 9
1#
b1000 -
1,
#3050
0!
03
#3055
1!
13
b1000 1
b0 9
0#
b1000 $
#3060
0!
03
#3065
1!
13
b1 9
1.
r6 =
0,
#3070
0!
03
#3075
1!
13
b10 9
b10000000 :
b0 ;
b10000000 -
0.
#3080
0!
03
#3085
1!
13
b1000000 :
b1000000 -
#3090
0!
03
